lfpykernels/__init__.py
lfpykernels/kernel_approximator.py
lfpykernels/version.py
lfpykernels/tests/BallAndSticksTemplate.hoc
lfpykernels/tests/BallAndSticks_E.hoc
lfpykernels/tests/exp2synI.mod
lfpykernels/tests/test_module.py
LFPykernels-0.2.0.dist-info/LICENSE
LFPykernels-0.2.0.dist-info/METADATA
LFPykernels-0.2.0.dist-info/WHEEL
LFPykernels-0.2.0.dist-info/top_level.txt
LFPykernels-0.2.0.dist-info/RECORD
