Metadata-Version: 2.1
Name: LFPykernels
Version: 0.2.0
Summary: Causal spike-signal impulse response functions for finite-sized neuronal network models
Home-page: https://github.com/LFPy/LFPykernels
Author: LFPy-team
Author-email: lfpy@users.noreply.github.com
Classifier: Programming Language :: Python :: 3
Classifier: Programming Language :: Python :: 3.7
Classifier: Programming Language :: Python :: 3.8
Classifier: Programming Language :: Python :: 3.9
Classifier: Programming Language :: Python :: 3.10
Classifier: License :: OSI Approved :: GNU General Public License (GPL)
Classifier: Operating System :: OS Independent
Classifier: Topic :: Scientific/Engineering
Classifier: Topic :: Scientific/Engineering :: Physics
Classifier: Topic :: Utilities
Classifier: Intended Audience :: Developers
Classifier: Intended Audience :: Science/Research
Classifier: Development Status :: 4 - Beta
Provides: lfpykernels
Requires-Python: >=3.7
License-File: LICENSE
Requires-Dist: LFPy (>=2.2.4)
Provides-Extra: docs
Requires-Dist: sphinx ; extra == 'docs'
Requires-Dist: numpydoc ; extra == 'docs'
Requires-Dist: sphinx-rtd-theme ; extra == 'docs'
Requires-Dist: recommonmark ; extra == 'docs'
Provides-Extra: tests
Requires-Dist: pytest ; extra == 'tests'
